odoo/addons/stock_location_zone/README.rst
odoo/addons/stock_location_zone/__init__.py
odoo/addons/stock_location_zone/__manifest__.py
odoo/addons/stock_location_zone/i18n/it.po
odoo/addons/stock_location_zone/i18n/stock_location_zone.pot
odoo/addons/stock_location_zone/i18n/zh_CN.po
odoo/addons/stock_location_zone/models/__init__.py
odoo/addons/stock_location_zone/models/stock_location.py
odoo/addons/stock_location_zone/readme/CONTRIBUTORS.rst
odoo/addons/stock_location_zone/readme/CREDITS.rst
odoo/addons/stock_location_zone/readme/DESCRIPTION.rst
odoo/addons/stock_location_zone/static/description/icon.png
odoo/addons/stock_location_zone/static/description/index.html
odoo/addons/stock_location_zone/views/stock_location.xml
odoo14_addon_stock_location_zone-14.0.1.0.1.dev6.dist-info/METADATA
odoo14_addon_stock_location_zone-14.0.1.0.1.dev6.dist-info/WHEEL
odoo14_addon_stock_location_zone-14.0.1.0.1.dev6.dist-info/top_level.txt
odoo14_addon_stock_location_zone-14.0.1.0.1.dev6.dist-info/RECORD
